feedmapper
example
