Metadata-Version: 1.0
Name: django-feedmapper
Version: 1.0.2
Summary: A utility for mapping feeds to Django models.
Home-page: https://github.com/natgeo/django-feedmapper
Author: National Geographic
Author-email: appdev@ngs.org
License: BSD
Platform: UNKNOWN
Classifier: Development Status :: 5 - Production/Stable
Classifier: Environment :: Web Environment
Classifier: Intended Audience :: Developers
Classifier: License :: OSI Approved :: BSD License
Classifier: Operating System :: OS Independent
Classifier: Programming Language :: Python
Classifier: Framework :: Django
